simpleANSI/__init__.py
simpleANSI/clear.py
simpleANSI/cursor.py
simpleANSI/graphics.py
simpleANSI-1.0.2.dist-info/LICENSE.txt
simpleANSI-1.0.2.dist-info/METADATA
simpleANSI-1.0.2.dist-info/WHEEL
simpleANSI-1.0.2.dist-info/top_level.txt
simpleANSI-1.0.2.dist-info/RECORD
