Metadata-Version: 2.1
Name: simpleANSI
Version: 1.0.2
Summary: A simple wrapper for ANSI escape codes
Home-page: https://github.com/AwesomeCronk/simpleANSI
Author: AwesomeCronk
Author-email: awesomecronk@gmail.com
License: MIT
Download-URL: https://pypi.org/project/simpleANSI
Keywords: ANSI
Platform: UNKNOWN
